[
  {
    "disease": "Third-Degree Burn",
    "keywords": ["charred", "white skin", "no pain burn", "black skin", "jala hua", "kaali chamdi", "dard nahi", "dard rahit jalan", "पूरी तरह जल गया", "काली चमड़ी", "थर्ड डिग्री बर्न"],
    "risk": "HIGH",
    "advice": "Emergency care required immediately"
  },
  {
    "disease": "Second-Degree Burn",
    "keywords": ["blisters", "burn swelling", "severe burn pain", "chaale", "fofole", "furan", "sujan", "bahut dard", "bhayankar jalan", "छाले", "सूजन", "बहुत दर्द", "तेज़ जलन"],
    "risk": "MEDIUM",
    "advice": "Medical attention required"
  },
  {
    "disease": "First-Degree Burn",
    "keywords": ["red skin", "mild burn", "burn pain", "laal chamdi", "halka jala", "jalan", "thoda jala", "लाल चमड़ी", "हल्का जला", "जलन", "थोड़ा जला"],
    "risk": "LOW",
    "advice": "Cool water, basic care"
  },
  {
    "disease": "Heart Attack",
    "keywords": ["chest pain", "shortness of breath", "irregular heartbeat", "pressure in chest", "chaati mein dard", "seene mein dard", "saans lene mein takleef", "saans phulna", "dharkan tej", "seene mein dabav", "heart pain", "dil ka daura", "chhati dard", "छाती में दर्द", "सीने में दर्द", "सांस फूलना", "दिल का दौरा", "हार्ट अटैक"],
    "risk": "RED",
    "advice": "Call emergency services immediately"
  },
  {
    "disease": "Stroke / Brain Hemorrhage",
    "keywords": ["unconscious", "seizure", "slurred speech", "paralysis", "sudden numbness", "behosh", "chakkar", "awaaz ladkhadana", "lakwa", "sunn padna", "bolne mein dikkat", "बेहोश", "चक्कर", "आवाज़ लड़खड़ाना", "लकवा", "सुन्न पड़ना", "बोलने में दिक्कत", "स्ट्रोक"],
    "risk": "RED",
    "advice": "Call emergency services immediately"
  },
  {
    "disease": "Severe Pneumonia / COVID-19",
    "keywords": ["severe cough", "difficulty breathing", "high fever", "chest tightness", "bahut khansi", "saans lene mein takleef", "tez bukhar", "seene mein jakdan", "बहुत खांसी", "सांस लेने में तकलीफ", "तेज़ बुखार", "सीने में जकड़न", "निमोनिया"],
    "risk": "RED",
    "advice": "Seek urgent medical care"
  },
  {
    "disease": "Dengue",
    "keywords": ["fever", "rash", "joint pain", "headache", "bukhar", "chakte", "jodon mein dard", "sir dard", "sirdard", "बुखार", "चकत्ते", "जोड़ों में दर्द", "सिर दर्द", "डेंगू"],
    "risk": "YELLOW",
    "advice": "Monitor symptoms and consult doctor"
  },
  {
    "disease": "Meningitis",
    "keywords": ["high fever", "stiff neck", "sensitivity to light", "vomiting", "confusion", "tez bukhar", "gardan akadna", "roshni se dikkat", "ulti", "chakkar", "dimagi bukhar", "तेज़ बुखार", "गर्दन अकड़ना", "रोशनी से दिक्कत", "उल्टी", "चक्कर", "दिमागी बुखार"],
    "risk": "RED",
    "advice": "Go to emergency care immediately"
  },
  {
    "disease": "Gastrointestinal Bleeding",
    "keywords": ["vomiting blood", "bloody stool", "severe dehydration", "dizziness", "khoon ki ulti", "khooni dast", "pani ki kami", "chakkar", "latrine mein khoon", "खून की उल्टी", "खूनी दस्त", "पानी की कमी", "चक्कर", "मल में खून"],
    "risk": "RED",
    "advice": "Seek urgent medical attention"
  },
  {
    "disease": "Appendicitis",
    "keywords": ["lower right abdominal pain", "nausea", "vomiting", "fever", "pet dard", "niche dard", "ulti", "bukhar", "matli", "pet ke nile hisse mein dard", "पेट दर्द", "उल्टी", "बुखार", "मतली", "अपेंडिक्स"],
    "risk": "HIGH",
    "advice": "Emergency surgery may be required"
  },
  {
    "disease": "Diabetic Ketoacidosis (DKA)",
    "keywords": ["excessive thirst", "frequent urination", "fruity breath", "confusion", "vomiting", "bahut pyaas", "baar baar peshab", "muh se meethi baas", "ulti", "sugar", "बहुत प्यास", "बार बार पेशाब", "मुंह से मीठी बास", "उल्टी", "शुगर", "डायबिटीज"],
    "risk": "RED",
    "advice": "Seek immediate hospital care"
  },
  {
    "disease": "Severe Asthma Attack",
    "keywords": ["difficulty breathing", "wheezing", "chest tightness", "blue lips", "saans lene mein takleef", "saans fulna", "siti ki awaz", "nile honth", "dama", "सांस लेने में तकलीफ", "सांस फूलना", "नीले होंठ", "दमा", "अस्थमा"],
    "risk": "RED",
    "advice": "Administer inhaler, call emergency services if worsening"
  },
  {
    "disease": "Seizure / Epileptic Attack",
    "keywords": ["convulsions", "loss of consciousness", "stiff body", "drooling", "daura", "behosh", "akadna", "laar tapakna", "mirgi", "दौरा", "बेहोश", "अकड़ना", "लार टपकना", "मिर्गी"],
    "risk": "HIGH",
    "advice": "Protect patient, seek medical help immediately"
  },
  {
    "disease": "Fever / Flu",
    "keywords": ["fever", "body ache", "chills", "cough", "sore throat", "bukhar", "badan dard", "thand lagna", "khansi", "gale mein kharash", "बुखार", "बदन दर्द", "ठंड लगना", "खांसी", "गले में खराश", "फ्लू"],
    "risk": "YELLOW",
    "advice": "Rest and monitor symptoms"
  },
  {
    "disease": "Common Cold",
    "keywords": ["cough", "cold", "sore throat", "runny nose", "khansi", "jukam", "gala kharab", "naak behna", "sardi", "खांसी", "जुकाम", "गला खराब", "नाक बहना", "सर्दी"],
    "risk": "GREEN",
    "advice": "Rest and basic care"
  },
  {
    "disease": "Food Poisoning",
    "keywords": ["vomiting", "diarrhea", "abdominal cramps", "nausea", "ulti", "dast", "pet mein marod", "pet dard", "matli", "उल्टी", "दस्त", "पेट में मरोड़", "पेट दर्द", "मतली", "फूड पॉइजनिंग"],
    "risk": "YELLOW",
    "advice": "Hydrate and consult doctor if severe"
  },
  {
    "disease": "Anaphylaxis / Severe Allergy",
    "keywords": ["difficulty breathing", "swelling", "hives", "rapid heartbeat", "loss of consciousness", "saans lene mein takleef", "sujan", "chakte", "tez dharkan", "behosh", "allergy", "सांस लेने में तकलीफ", "सूजन", "चकत्ते", "तेज़ धड़कन", "बेहोश", "एलर्जी"],
    "risk": "RED",
    "advice": "Inject epinephrine and call emergency services immediately"
  },
  {
    "disease": "Viral Infection / Sore Throat",
    "keywords": ["throat pain", "sore throat", "tonsil", "gale mein dard", "gala kharab", "kharash", "tonsils", "गले में दर्द", "गला खराब", "खराश"],
    "risk": "LOW",
    "advice": "Gargle with warm salt water and rest"
  },
  {
    "disease": "Mild Dehydration",
    "keywords": ["thirsty", "dry mouth", "weakness", "lethargy", "pyas", "thakan", "kamzori", "muh sukhna", "pyaas", "थकान", "कमजोरी", "प्यास"],
    "risk": "LOW",
    "advice": "Drink ORS or plain water frequently"
  },
  {
    "disease": "Sprain / Muscle Strain",
    "keywords": ["muscle pain", "joint pain", "sprain", "moch", "khichav", "badan dard", "nas chadhna", "jodon mein dard", "मोच", "खिंचाव", "मांसपेशियों में दर्द"],
    "risk": "LOW",
    "advice": "Rest the injured area and apply ice"
  },
  {
    "disease": "Minor Cuts / Scrapes",
    "keywords": ["cut", "scrape", "minor bleeding", "chot", "kharoch", "chhil jana", "choti chot", "halka khoon", "चोट", "खरोंच", "कट लगना"],
    "risk": "GREEN",
    "advice": "Clean with soap and water, apply a bandage"
  },
  {
    "disease": "Skin Allergy / Mild Rash",
    "keywords": ["itching", "red spots", "hives", "rash", "khujli", "lal daane", "lal dhabbe", "allergy", "chakte", "खुजली", "लाल दाने", "एलर्जी"],
    "risk": "LOW",
    "advice": "Keep area clean, use anti-allergic cream if needed"
  },
  {
    "disease": "Gastritis / Acidity",
    "keywords": ["acid reflux", "heartburn", "stomach burn", "gas", "acidity", "jalan", "pet mein jalan", "seene mein jalan", "pet fulna", "गैस", "पेट में जलन", "एसिडिटी"],
    "risk": "LOW",
    "advice": "Take antacids, avoid spicy food"
  },
  {
    "disease": "Migraine / Tension Headache",
    "keywords": ["headache", "head pain", "throbbing head", "sir dard", "sir dukhna", "sirdard", "tez sir dard", "aadha sir dard", "migraine", "सिर दर्द", "माइग्रेन"],
    "risk": "MEDIUM",
    "advice": "Rest in a quiet room and take pain relievers if prescribed"
  },
  {
    "disease": "Minor Eye Infection / Conjunctivitis",
    "keywords": ["red eye", "eye pain", "watery eyes", "pink eye", "aankh aana", "laal aankh", "aankh lal hona", "aankh mein dard", "लाल आंख", "आंख आना"],
    "risk": "LOW",
    "advice": "Use prescribed eye drops, do not rub eyes"
  },
  {
    "disease": "Urinary Tract Infection (UTI)",
    "keywords": ["painful urination", "burning urine", "frequent urge to urinate", "peshab mein jalan", "baar baar peshab", "peshab dard", "पेशाब में जलन", "यूरिन इन्फेक्शन"],
    "risk": "MEDIUM",
    "advice": "Drink plenty of water and consult a doctor"
  },
  {
    "disease": "Ear Infection",
    "keywords": ["ear pain", "ear ache", "fluid from ear", "kaan dard", "kaan behna", "kaan dukhna", "kaan sunn padna", "कान दर्द", "कान बहना"],
    "risk": "LOW",
    "advice": "Consult a doctor for ear drops, avoid putting objects in ear"
  }
]